omegaup/__init__.py
omegaup/api.py
omegaup/py.typed
omegaup/validator/__init__.py
omegaup/validator/validatortest.py
omegaup-2.0.18.dist-info/LICENSE
omegaup-2.0.18.dist-info/METADATA
omegaup-2.0.18.dist-info/WHEEL
omegaup-2.0.18.dist-info/top_level.txt
omegaup-2.0.18.dist-info/RECORD
